gabarra/__init__.py
gabarra/data_analysis/__init__.py
gabarra/data_analysis/data_analysis.py
gabarra/data_processing/__init__.py
gabarra/data_processing/data_processing.py
gabarra/data_visualization/__init__.py
gabarra/data_visualization/data_visualization.py
gabarra/machine_learning/__init__.py
gabarra/machine_learning/machine_learning.py
gabarra-0.0.1.dist-info/LICENSE
gabarra-0.0.1.dist-info/METADATA
gabarra-0.0.1.dist-info/WHEEL
gabarra-0.0.1.dist-info/top_level.txt
gabarra-0.0.1.dist-info/RECORD
