Metadata-Version: 2.1
Name: gabarra
Version: 0.0.1
Summary: Data science library
Author-email: Ekaitz San Roman <ekaitz77@gmail.com>, Iñigo Auzmendi <iauzmendipinedo@gmail.com>, Adrian Sarikaya <adri-kh93@hotmail.com>, Pablo Pozos <pablo.pozo.vargas@gmail.com>, Karen Fajardo <karenfajardo.sa@gmail.com>, Ivan Fernandez <ivan.fdez.luperena@gmail.com>, Gaizka Torre <torreggb@gmail.com>, Carlota Mingo <mingoirache@gmail.com>, Cristina Fernandez <cristina.fernandez@txorierri.com>, Jessica Rodriguez <jcrdzg@gmail.com>, Adolfo Campos <adolfogutcampos@gmail.com>, Adrian Ruiz <adrian
Project-URL: Homepage, https://github.com/sirtxo/GABARRA
Project-URL: Issues, https://github.com/sirtxo/GABARRA/issues
Classifier: Programming Language :: Python :: 3
Classifier: License :: OSI Approved :: MIT License
Classifier: Operating System :: OS Independent
Requires-Python: >=3.8
License-File: LICENSE
